README.md
setup.py
squareconnect/__init__.py
squareconnect/api_client.py
squareconnect/configuration.py
squareconnect/rest.py
squareconnect.egg-info/PKG-INFO
squareconnect.egg-info/SOURCES.txt
squareconnect.egg-info/dependency_links.txt
squareconnect.egg-info/requires.txt
squareconnect.egg-info/top_level.txt
squareconnect/apis/__init__.py
squareconnect/apis/apple_pay_api.py
squareconnect/apis/catalog_api.py
squareconnect/apis/checkout_api.py
squareconnect/apis/customers_api.py
squareconnect/apis/employees_api.py
squareconnect/apis/inventory_api.py
squareconnect/apis/labor_api.py
squareconnect/apis/locations_api.py
squareconnect/apis/mobile_authorization_api.py
squareconnect/apis/o_auth_api.py
squareconnect/apis/orders_api.py
squareconnect/apis/reporting_api.py
squareconnect/apis/transactions_api.py
squareconnect/apis/v1_employees_api.py
squareconnect/apis/v1_items_api.py
squareconnect/apis/v1_locations_api.py
squareconnect/apis/v1_transactions_api.py
squareconnect/models/__init__.py
squareconnect/models/additional_recipient.py
squareconnect/models/additional_recipient_receivable.py
squareconnect/models/additional_recipient_receivable_refund.py
squareconnect/models/address.py
squareconnect/models/batch_change_inventory_request.py
squareconnect/models/batch_change_inventory_response.py
squareconnect/models/batch_delete_catalog_objects_request.py
squareconnect/models/batch_delete_catalog_objects_response.py
squareconnect/models/batch_retrieve_catalog_objects_request.py
squareconnect/models/batch_retrieve_catalog_objects_response.py
squareconnect/models/batch_retrieve_inventory_changes_request.py
squareconnect/models/batch_retrieve_inventory_changes_response.py
squareconnect/models/batch_retrieve_inventory_counts_request.py
squareconnect/models/batch_retrieve_inventory_counts_response.py
squareconnect/models/batch_retrieve_orders_request.py
squareconnect/models/batch_retrieve_orders_response.py
squareconnect/models/batch_upsert_catalog_objects_request.py
squareconnect/models/batch_upsert_catalog_objects_response.py
squareconnect/models/break_type.py
squareconnect/models/business_hours.py
squareconnect/models/business_hours_period.py
