Metadata-Version: 2.1
Name: squareconnect
Version: 2.20190724.1
Summary: Square Connect v2 Python Client
Home-page: https://github.com/square/connect-python-sdk
Author: Square Inc.
Author-email: 
License: http://www.apache.org/licenses/LICENSE-2.0
Keywords: Swagger,Square Connect API
Platform: UNKNOWN
